gqltype/__init__.py
gqltype/context.py
gqltype/contrib/__init__.py
gqltype/contrib/aiohttp/__init__.py
gqltype/contrib/aiohttp/view.py
gqltype/contrib/connection/__init__.py
gqltype/contrib/graphiql_page.py
gqltype/contrib/starlette/__init__.py
gqltype/contrib/starlette/view.py
gqltype/decorators.py
gqltype/exceptions.py
gqltype/graphql_types/__init__.py
gqltype/graphql_types/date.py
gqltype/graphql_types/datetime.py
gqltype/graphql_types/decimal.py
gqltype/graphql_types/duration.py
gqltype/graphql_types/nothing.py
gqltype/graphql_types/time.py
gqltype/graphql_types/uuid.py
gqltype/schema.py
gqltype/transform/__init__.py
gqltype/transform/transform_class.py
gqltype/transform/transform_enum.py
gqltype/transform/transform_general_type.py
gqltype/transform/transform_graphql_type.py
gqltype/transform/transform_nothing_type.py
gqltype/transform/transform_type_hint.py
gqltype/transform/transform_union.py
gqltype/transform/transformer.py
gqltype/transform/type_container.py
gqltype/utils/__init__.py
gqltype/utils/camel_case.py
gqltype/utils/cls.py
gqltype/utils/func.py
gqltype/utils/resolver.py
gqltype/utils/types.py
gqltype-0.1.2.dist-info/WHEEL
gqltype-0.1.2.dist-info/METADATA
gqltype-0.1.2.dist-info/RECORD
