Metadata-Version: 2.1
Name: gqltype
Version: 0.1.2
Summary: Simple way to define GraphQL schema
Home-page: https://github.com/miphreal/gqltype
License: MIT
Keywords: GraphQL,schema,graphql-core
Author: miphreal
Author-email: miphreal@gmail.com
Requires-Python: >=3.6,<3.9
Classifier: License :: OSI Approved :: MIT License
Classifier: Programming Language :: Python :: 3
Classifier: Programming Language :: Python :: 3.6
Classifier: Programming Language :: Python :: 3.7
Classifier: Programming Language :: Python :: 3.8
Requires-Dist: aniso8601
Requires-Dist: graphql-core (>=3.0)
Project-URL: Documentation, https://github.com/miphreal/gqltype
Project-URL: Repository, https://github.com/miphreal/gqltype
